{
  "/include/ajax/nikolaus_pizza.php-7" : {
    "transaction" : "/include/ajax/nikolaus_pizza.php-7",
    "sampleCount" : 10,
    "errorCount" : 0,
    "errorPct" : 0.0,
    "meanResTime" : 65.6,
    "medianResTime" : 66.0,
    "minResTime" : 60.0,
    "maxResTime" : 77.0,
    "pct1ResTime" : 76.2,
    "pct2ResTime" : 77.0,
    "pct3ResTime" : 77.0,
    "throughput" : 6.309148264984227,
    "receivedKBytesPerSec" : 6.974566246056782,
    "sentKBytesPerSec" : 3.4503154574132493
  },
  "/upload/resize_cache/iblock/b40/100_100_1/zribf5ykbp222cgylfsm17d099ub4pzk.jpg-6" : {
    "transaction" : "/upload/resize_cache/iblock/b40/100_100_1/zribf5ykbp222cgylfsm17d099ub4pzk.jpg-6",
    "sampleCount" : 10,
    "errorCount" : 0,
    "errorPct" : 0.0,
    "meanResTime" : 42.4,
    "medianResTime" : 42.0,
    "minResTime" : 39.0,
    "maxResTime" : 46.0,
    "pct1ResTime" : 45.9,
    "pct2ResTime" : 46.0,
    "pct3ResTime" : 46.0,
    "throughput" : 6.39386189258312,
    "receivedKBytesPerSec" : 30.72050831202046,
    "sentKBytesPerSec" : 2.8909746643222505
  },
  "/include/ajax/ym_ecommerce.php-8" : {
    "transaction" : "/include/ajax/ym_ecommerce.php-8",
    "sampleCount" : 10,
    "errorCount" : 0,
    "errorPct" : 0.0,
    "meanResTime" : 88.1,
    "medianResTime" : 87.0,
    "minResTime" : 83.0,
    "maxResTime" : 101.0,
    "pct1ResTime" : 100.0,
    "pct2ResTime" : 101.0,
    "pct3ResTime" : 101.0,
    "throughput" : 6.207324643078834,
    "receivedKBytesPerSec" : 5.461718265052762,
    "sentKBytesPerSec" : 3.1521570453134697
  },
  "/checkout/-9" : {
    "transaction" : "/checkout/-9",
    "sampleCount" : 10,
    "errorCount" : 0,
    "errorPct" : 0.0,
    "meanResTime" : 110.6,
    "medianResTime" : 110.5,
    "minResTime" : 98.0,
    "maxResTime" : 127.0,
    "pct1ResTime" : 126.8,
    "pct2ResTime" : 127.0,
    "pct3ResTime" : 127.0,
    "throughput" : 6.105006105006105,
    "receivedKBytesPerSec" : 41.53252346611722,
    "sentKBytesPerSec" : 2.9571123321123323
  },
  "Total" : {
    "transaction" : "Total",
    "sampleCount" : 110,
    "errorCount" : 0,
    "errorPct" : 0.0,
    "meanResTime" : 115.80000000000001,
    "medianResTime" : 83.5,
    "minResTime" : 39.0,
    "maxResTime" : 1130.0,
    "pct1ResTime" : 130.60000000000002,
    "pct2ResTime" : 342.4499999999984,
    "pct3ResTime" : 1122.41,
    "throughput" : 43.06969459671104,
    "receivedKBytesPerSec" : 174.6582413615897,
    "sentKBytesPerSec" : 21.66867536217698
  },
  "/upload/resize_cache/iblock/b40/150_150_1/zribf5ykbp222cgylfsm17d099ub4pzk.jpg-11" : {
    "transaction" : "/upload/resize_cache/iblock/b40/150_150_1/zribf5ykbp222cgylfsm17d099ub4pzk.jpg-11",
    "sampleCount" : 10,
    "errorCount" : 0,
    "errorPct" : 0.0,
    "meanResTime" : 42.8,
    "medianResTime" : 42.5,
    "minResTime" : 40.0,
    "maxResTime" : 46.0,
    "pct1ResTime" : 46.0,
    "pct2ResTime" : 46.0,
    "pct3ResTime" : 46.0,
    "throughput" : 6.325110689437065,
    "receivedKBytesPerSec" : 61.16950308349146,
    "sentKBytesPerSec" : 2.9154807084123973
  },
  "/include/ajax/nikolaus_pizza.php-1" : {
    "transaction" : "/include/ajax/nikolaus_pizza.php-1",
    "sampleCount" : 10,
    "errorCount" : 0,
    "errorPct" : 0.0,
    "meanResTime" : 533.3,
    "medianResTime" : 349.5,
    "minResTime" : 139.0,
    "maxResTime" : 1130.0,
    "pct1ResTime" : 1123.1,
    "pct2ResTime" : 1130.0,
    "pct3ResTime" : 1130.0,
    "throughput" : 5.555555555555555,
    "receivedKBytesPerSec" : 10.546875,
    "sentKBytesPerSec" : 3.0327690972222223
  },
  "/upload/resize_cache/iblock/c2f/150_150_1/jolfm1cmof3yfsvr91utri8ioggkcr1f.jpg-10" : {
    "transaction" : "/upload/resize_cache/iblock/c2f/150_150_1/jolfm1cmof3yfsvr91utri8ioggkcr1f.jpg-10",
    "sampleCount" : 10,
    "errorCount" : 0,
    "errorPct" : 0.0,
    "meanResTime" : 43.3,
    "medianResTime" : 42.5,
    "minResTime" : 41.0,
    "maxResTime" : 49.0,
    "pct1ResTime" : 48.7,
    "pct2ResTime" : 49.0,
    "pct3ResTime" : 49.0,
    "throughput" : 6.297229219143577,
    "receivedKBytesPerSec" : 96.2971800220403,
    "sentKBytesPerSec" : 2.902629093198992
  },
  "/include/ajax/ym_ecommerce.php-2" : {
    "transaction" : "/include/ajax/ym_ecommerce.php-2",
    "sampleCount" : 10,
    "errorCount" : 0,
    "errorPct" : 0.0,
    "meanResTime" : 98.2,
    "medianResTime" : 95.5,
    "minResTime" : 86.0,
    "maxResTime" : 131.0,
    "pct1ResTime" : 128.0,
    "pct2ResTime" : 131.0,
    "pct3ResTime" : 131.0,
    "throughput" : 6.234413965087282,
    "receivedKBytesPerSec" : 5.260286783042393,
    "sentKBytesPerSec" : 3.165913341645885
  },
  "/include/ajax/nikolaus_pizza.php-3" : {
    "transaction" : "/include/ajax/nikolaus_pizza.php-3",
    "sampleCount" : 10,
    "errorCount" : 0,
    "errorPct" : 0.0,
    "meanResTime" : 96.89999999999999,
    "medianResTime" : 97.0,
    "minResTime" : 89.0,
    "maxResTime" : 103.0,
    "pct1ResTime" : 103.0,
    "pct2ResTime" : 103.0,
    "pct3ResTime" : 103.0,
    "throughput" : 6.20347394540943,
    "receivedKBytesPerSec" : 10.904544044665013,
    "sentKBytesPerSec" : 3.3864667338709675
  },
  "/include/ajax/ym_ecommerce.php-4" : {
    "transaction" : "/include/ajax/ym_ecommerce.php-4",
    "sampleCount" : 10,
    "errorCount" : 0,
    "errorPct" : 0.0,
    "meanResTime" : 87.8,
    "medianResTime" : 86.5,
    "minResTime" : 80.0,
    "maxResTime" : 103.0,
    "pct1ResTime" : 101.9,
    "pct2ResTime" : 103.0,
    "pct3ResTime" : 103.0,
    "throughput" : 6.238303181534623,
    "receivedKBytesPerSec" : 5.488975748596382,
    "sentKBytesPerSec" : 3.1678883343730506
  },
  "/include/ajax/nikolaus_pizza.php-5" : {
    "transaction" : "/include/ajax/nikolaus_pizza.php-5",
    "sampleCount" : 10,
    "errorCount" : 0,
    "errorPct" : 0.0,
    "meanResTime" : 64.8,
    "medianResTime" : 64.0,
    "minResTime" : 61.0,
    "maxResTime" : 69.0,
    "pct1ResTime" : 69.0,
    "pct2ResTime" : 69.0,
    "pct3ResTime" : 69.0,
    "throughput" : 6.297229219143577,
    "receivedKBytesPerSec" : 4.230950881612091,
    "sentKBytesPerSec" : 3.234709540302267
  }
}